mds_periodic_invoice-4.6.0.dist-info/DESCRIPTION.rst
mds_periodic_invoice-4.6.0.dist-info/METADATA
mds_periodic_invoice-4.6.0.dist-info/RECORD
mds_periodic_invoice-4.6.0.dist-info/WHEEL
mds_periodic_invoice-4.6.0.dist-info/entry_points.txt
mds_periodic_invoice-4.6.0.dist-info/metadata.json
mds_periodic_invoice-4.6.0.dist-info/top_level.txt
trytond/modules/periodic_invoice/README.rst
trytond/modules/periodic_invoice/__init__.py
trytond/modules/periodic_invoice/configuration.py
trytond/modules/periodic_invoice/configuration.xml
trytond/modules/periodic_invoice/constrepeat.py
trytond/modules/periodic_invoice/cronjob.xml
trytond/modules/periodic_invoice/invoicetempl.py
trytond/modules/periodic_invoice/invoicetempl.xml
trytond/modules/periodic_invoice/menuicons.xml
trytond/modules/periodic_invoice/role_config_admin.xml
trytond/modules/periodic_invoice/role_cronjob.xml
trytond/modules/periodic_invoice/role_invtempl_edit.xml
trytond/modules/periodic_invoice/role_invtempl_view.xml
trytond/modules/periodic_invoice/tryton.cfg
trytond/modules/periodic_invoice/icon/calendar.svg
trytond/modules/periodic_invoice/locale/de.po
trytond/modules/periodic_invoice/view/configuration_form.xml
trytond/modules/periodic_invoice/view/invline_form.xml
trytond/modules/periodic_invoice/view/invline_tree.xml
trytond/modules/periodic_invoice/view/invline_tree_sequence.xml
trytond/modules/periodic_invoice/view/invoice_form.xml
trytond/modules/periodic_invoice/view/invoice_tree.xml
